opentelemetry/instrumentation/openai_agents/__init__.py
opentelemetry/instrumentation/openai_agents/_hooks.py
opentelemetry/instrumentation/openai_agents/_realtime_wrappers.py
opentelemetry/instrumentation/openai_agents/utils.py
opentelemetry/instrumentation/openai_agents/version.py
opentelemetry_instrumentation_openai_agents-0.51.1.dist-info/METADATA
opentelemetry_instrumentation_openai_agents-0.51.1.dist-info/WHEEL
opentelemetry_instrumentation_openai_agents-0.51.1.dist-info/entry_points.txt
opentelemetry_instrumentation_openai_agents-0.51.1.dist-info/RECORD
